{"主導企業名稱":"佳和實業股份有限公司","計畫起訖時間":"90年10月1日 至 92年9月30日","計畫總經費":"32,073 仟元","計畫補助款":"9,096 仟元","計畫自籌款":"22,977 仟元","計畫概述":"<td valign=\"top\">\n\t\t<table width=\"90%\" border=\"0\">\n<tr style=\"line-height:150%\">\n<td valign=\"top\"><b>(一) 計畫內容<\/b><\/td>\n\t\t\t<\/tr>\n<tr>\n<td valign=\"top\">\n<ol>\n<li>該計畫係以建立織布業完整上下游e化體系為目標，以佳和為中心，連結國際品牌服飾業者如：Polo、VH，國際成衣大廠如：聯業、聯泰，國際貿易商如：Active \r\n  Sight、長億等客戶，提供產品資訊、客戶索樣、打樣打色、生產進度、樣本庫存、線上VIP展示空間等多種客戶迫切需要之即時資訊，協助客戶有效拓展商機，以建立更緊密之業務合作關係；向上與國內原物料供應商如：新光、新市等廠商連結，交換客訴及失敗案例資訊，以做為產品改善之依據，提昇公司產品品質。<br><br>\n<\/li>\n<li>本計畫包含<br><br><ul>\n<li>產品推廣系統\r\n    <\/li>\n<li>打樣打色系統\r\n    <\/li>\n<li>客訴管理系統\r\n    <\/li>\n<li>客戶管理系統\r\n    <\/li>\n<li>企業入口網站<\/li>\n<\/ul>\n<\/li>\n<\/ol>\n<blockquote style=\"MARGIN-RIGHT: 0px\">\r\n  <p>等5個系統模組。<\/p>\n<\/blockquote>\r\n<\/td>\n\t\t\t<\/tr>\n<tr style=\"line-height:150%\">\n<td valign=\"top\">\n<br><b>(二) 預期效益<\/b>\n<\/td>\n\t\t\t<\/tr>\n<tr>\n<td valign=\"top\">\n<p>一、量化效益： \r\n<\/p>\n<ol>\n<li>將客戶產品sourcing時間從目前60天縮短至51天\r\n  <\/li>\n<li>將打樣時間從目前15天縮短至10天\r\n  <\/li>\n<li>因上述二項作業處理時間縮短，使成衣生產之追加單交期加速14天，若依追加單交期每加速7天，成衣可少折扣損失5%計算，加速14天可少折扣損失10%為計算基礎，一年可減少之折扣損失約達559,200仟元。<\/li>\n<\/ol>\n<p>二、非量化效益： \r\n<\/p>\n<ol>\n<li>本計畫連結國際級之成衣集團，如Active Sight、聯業集團，及全球知名通路及服飾品牌業者，如Polo、Phylips Ven \r\n  Heusen(VH)等，可提昇我國織布業之國際能見度。\r\n  <\/li>\n<li>藉由建立織布產業上下游整合e化體系，加強與客戶及供應商間之緊密合作關係，增進從研發產品、推廣、打樣、試單到大量追加之運作效率，以保有對韓國、中國大陸等競爭對手之領先優勢，甚至有超越日本之機會。<\/li>\n<\/ol>\n<\/td>\n\t\t\t<\/tr>\n<\/table>\n<\/td>"}